mootdx/__init__.py
mootdx/__main__.py
mootdx/affair.py
mootdx/config.py
mootdx/consts.py
mootdx/quotes.py
mootdx/reader.py
mootdx/server.py
mootdx/trader.py
mootdx/utils.py
mootdx/contrib/__init__.py
mootdx/contrib/datafq.py
mootdx/financial/__init__.py
mootdx/financial/base.py
mootdx/financial/financial.py
mootdxpro-1.3.18.dist-info/AUTHORS.rst
mootdxpro-1.3.18.dist-info/LICENSE
mootdxpro-1.3.18.dist-info/METADATA
mootdxpro-1.3.18.dist-info/WHEEL
mootdxpro-1.3.18.dist-info/entry_points.txt
mootdxpro-1.3.18.dist-info/top_level.txt
mootdxpro-1.3.18.dist-info/RECORD
