Metadata-Version: 2.1
Name: mootdxpro
Version: 1.3.18
Summary: 通达信数据读取接口.
Home-page: https://github.com/yanjlee/mootdx
Author: yanjlee
Author-email: yanjlee@163.com
License: MIT license
Keywords: mootdx
Classifier: Development Status :: 2 - Pre-Alpha
Classifier: Intended Audience :: Developers
Classifier: License :: OSI Approved :: MIT License
Classifier: Natural Language :: English
Classifier: Programming Language :: Python :: 3
Classifier: Programming Language :: Python :: 3.5
Classifier: Programming Language :: Python :: 3.6
Classifier: Programming Language :: Python :: 3.7
License-File: LICENSE
License-File: AUTHORS.rst
Requires-Dist: click >=6.7
Requires-Dist: pandas >=0.23.3
Requires-Dist: prettytable >=0.7.2
Requires-Dist: pytdx >=1.67
Requires-Dist: tqdm >=4.37.0
Requires-Dist: pytest
